newsp-0.23.data/scripts/newsp
newspp/ImageHelper.py
newspp/NewsHelper.py
newspp/__init__.py
newsp-0.23.dist-info/METADATA
newsp-0.23.dist-info/WHEEL
newsp-0.23.dist-info/top_level.txt
newsp-0.23.dist-info/RECORD
