Metadata-Version: 2.1
Name: newsp
Version: 0.23
Summary: A Des of newsp
Home-page: https://github.com/vtandroid/newsp
Author: Thanh Hoa
Author-email: getmoneykhmt3@gmail.com
License: UNKNOWN
Platform: UNKNOWN
Classifier: Programming Language :: Python :: 3
Classifier: License :: OSI Approved :: MIT License
Classifier: Operating System :: OS Independent
Requires-Dist: newspaper3k
Requires-Dist: awesome-slugify
Requires-Dist: pillow
Requires-Dist: spacy
